palm_4u_preprocessor_oap/__init__.py
palm_4u_preprocessor_oap/palm_4u_preprocessor.py
palm_4u_preprocessor_oap/udt2palm_runner.py
palm_4u_preprocessor_oap-0.0.4.dist-info/METADATA
palm_4u_preprocessor_oap-0.0.4.dist-info/WHEEL
palm_4u_preprocessor_oap-0.0.4.dist-info/RECORD
