Metadata-Version: 2.4
Name: palm_4u_preprocessor_oap
Version: 0.0.4
Summary: Preprocessor for Palm 4U
Maintainer-email: "terrestris GmbH & Co. KG" <info@terrestris.de>
Classifier: License :: OSI Approved :: BSD License
Classifier: Programming Language :: Python :: 3.12
Provides-Extra: publish
Requires-Dist: build; extra == 'publish'
Requires-Dist: twine; extra == 'publish'
